NiukeChanpinJingliQiuzhiJingyanFenxiang20212022Fix1/README.md
NiukeChanpinJingliQiuzhiJingyanFenxiang20212022Fix1/__init__.py
NiukeChanpinJingliQiuzhiJingyanFenxiang20212022Fix1/__main__.py
NiukeChanpinJingliQiuzhiJingyanFenxiang20212022Fix1/file.epub
NiukeChanpinJingliQiuzhiJingyanFenxiang20212022Fix1/index.html
NiukeChanpinJingliQiuzhiJingyanFenxiang20212022Fix1/css/__init__.py
NiukeChanpinJingliQiuzhiJingyanFenxiang20212022Fix1/css/annotations.css
NiukeChanpinJingliQiuzhiJingyanFenxiang20212022Fix1/css/main.css
NiukeChanpinJingliQiuzhiJingyanFenxiang20212022Fix1/css/normalize.css
NiukeChanpinJingliQiuzhiJingyanFenxiang20212022Fix1/css/popup.css
NiukeChanpinJingliQiuzhiJingyanFenxiang20212022Fix1/font/__init__.py
NiukeChanpinJingliQiuzhiJingyanFenxiang20212022Fix1/font/fontello.eot
NiukeChanpinJingliQiuzhiJingyanFenxiang20212022Fix1/font/fontello.svg
NiukeChanpinJingliQiuzhiJingyanFenxiang20212022Fix1/font/fontello.ttf
NiukeChanpinJingliQiuzhiJingyanFenxiang20212022Fix1/font/fontello.woff
NiukeChanpinJingliQiuzhiJingyanFenxiang20212022Fix1/img/__init__.py
NiukeChanpinJingliQiuzhiJingyanFenxiang20212022Fix1/img/annotator-glyph-sprite.png
NiukeChanpinJingliQiuzhiJingyanFenxiang20212022Fix1/img/annotator-icon-sprite.png
NiukeChanpinJingliQiuzhiJingyanFenxiang20212022Fix1/img/apple-touch-icon.png
NiukeChanpinJingliQiuzhiJingyanFenxiang20212022Fix1/img/cancelfullscreen.png
NiukeChanpinJingliQiuzhiJingyanFenxiang20212022Fix1/img/close.png
NiukeChanpinJingliQiuzhiJingyanFenxiang20212022Fix1/img/fullscreen.png
NiukeChanpinJingliQiuzhiJingyanFenxiang20212022Fix1/img/loader.gif
NiukeChanpinJingliQiuzhiJingyanFenxiang20212022Fix1/img/menu-icon.png
NiukeChanpinJingliQiuzhiJingyanFenxiang20212022Fix1/img/save.png
NiukeChanpinJingliQiuzhiJingyanFenxiang20212022Fix1/img/saved.png
NiukeChanpinJingliQiuzhiJingyanFenxiang20212022Fix1/img/settings-s.png
NiukeChanpinJingliQiuzhiJingyanFenxiang20212022Fix1/img/settings.png
niuke_chanpin_jingli_qiuzhi_jingyan_fenxiang_2021_2022_fix1-2025.3.25.0.dist-info/METADATA
niuke_chanpin_jingli_qiuzhi_jingyan_fenxiang_2021_2022_fix1-2025.3.25.0.dist-info/WHEEL
niuke_chanpin_jingli_qiuzhi_jingyan_fenxiang_2021_2022_fix1-2025.3.25.0.dist-info/entry_points.txt
niuke_chanpin_jingli_qiuzhi_jingyan_fenxiang_2021_2022_fix1-2025.3.25.0.dist-info/top_level.txt
niuke_chanpin_jingli_qiuzhi_jingyan_fenxiang_2021_2022_fix1-2025.3.25.0.dist-info/RECORD
